pydantic_ro_crates/__init__.py
pydantic_ro_crates/assets/css/home-button.css
pydantic_ro_crates/assets/css/ro-crate-preview.css
pydantic_ro_crates/assets/img/mgnify-logo.svg
pydantic_ro_crates/assets/js/home-button.js
pydantic_ro_crates/assets/js/ro-crate-preview.js
pydantic_ro_crates/contrib/__init__.py
pydantic_ro_crates/contrib/dataviz/VegaLiteVisualisation.py
pydantic_ro_crates/contrib/dataviz/__init__.py
pydantic_ro_crates/contrib/dataviz/histogram.py
pydantic_ro_crates/contrib/dataviz/make_visualisation.py
pydantic_ro_crates/contrib/dataviz/vega-lite-context.json
pydantic_ro_crates/contrib/mapping/__init__.py
pydantic_ro_crates/contrib/mapping/render_map.py
pydantic_ro_crates/contrib/mapping/templates/leaflet.j2
pydantic_ro_crates/crate/__init__.py
pydantic_ro_crates/crate/ro_crate.py
pydantic_ro_crates/graph/__init__.py
pydantic_ro_crates/graph/models.py
pydantic_ro_crates/preview/__init__.py
pydantic_ro_crates/preview/render.py
pydantic_ro_crates/preview/templates/crate-preview.j2
pydantic_ro_crates/preview/templates/style.j2
pydantic_ro_crates-0.3.0.dist-info/LICENSE
pydantic_ro_crates-0.3.0.dist-info/METADATA
pydantic_ro_crates-0.3.0.dist-info/WHEEL
pydantic_ro_crates-0.3.0.dist-info/RECORD
