Metadata-Version: 2.3
Name: pydantic-ro-crates
Version: 0.3.0
Summary: Create Research Object Crates (RO-Crates) using Pydantic types
License: Apache-2.0
Author: Sandy Rogers
Author-email: sandyr@ebi.ac.uk
Requires-Python: >=3.11,<4.0
Classifier: License :: OSI Approved :: Apache Software License
Classifier: Programming Language :: Python :: 3
Classifier: Programming Language :: Python :: 3.11
Classifier: Programming Language :: Python :: 3.12
Classifier: Programming Language :: Python :: 3.13
Requires-Dist: altair[all] (>=5.5.0,<6.0.0)
Requires-Dist: arcp (>=0.2.1,<0.3.0)
Requires-Dist: beautifulsoup4 (>=4.12.3,<5.0.0)
Requires-Dist: jinja2 (>=3.1.4,<4.0.0)
Requires-Dist: pandas (>=2.2.3,<3.0.0)
Requires-Dist: pydantic (>=2.9.2,<3.0.0)
Requires-Dist: pydantic2-schemaorg (>=0.3.0,<0.4.0)
Requires-Dist: requests (>=2.32.3,<3.0.0)
Requires-Dist: tqdm (>=4.67.0,<5.0.0)
